cemilkoca/__init__.py
cemilkoca/statistics.py
cemilkoca-0.0.1.dist-info/METADATA
cemilkoca-0.0.1.dist-info/WHEEL
cemilkoca-0.0.1.dist-info/top_level.txt
cemilkoca-0.0.1.dist-info/RECORD
