Metadata-Version: 2.4
Name: cemilkoca
Version: 0.0.1
Summary: A simple package for calculating statistics.
Author-email: Cemil Koca <cemo19031903@hotmail.com>
Project-URL: Homepage, https://github.com/ckaemm/cemilkoca
Keywords: cemilkoca,statistics
Classifier: Development Status :: 3 - Alpha
Classifier: Intended Audience :: Developers
Classifier: License :: OSI Approved :: MIT License
Classifier: Programming Language :: Python :: 3
Classifier: Operating System :: OS Independent
Requires-Python: >=3.6.0
